awsmpi/__init__.py
awsmpi/awsapi.py
awsmpi/entrypoint.py
awsmpi-1.5a0.dist-info/DESCRIPTION.rst
awsmpi-1.5a0.dist-info/METADATA
awsmpi-1.5a0.dist-info/RECORD
awsmpi-1.5a0.dist-info/WHEEL
awsmpi-1.5a0.dist-info/entry_points.txt
awsmpi-1.5a0.dist-info/metadata.json
awsmpi-1.5a0.dist-info/top_level.txt
