Metadata-Version: 2.0
Name: awsmpi
Version: 1.5a0
Summary: Manage mpi cluster on AWS.
Home-page: https://github.com/WenbinHou/awsmpi
Author: Wenbin Hou
Author-email: catchyrime@fastmail.com
License: AGPLv3
Keywords: aws mpi
Platform: UNKNOWN
Classifier: Development Status :: 3 - Alpha
Classifier: Environment :: Console
Classifier: Intended Audience :: Developers
Classifier: License :: OSI Approved :: GNU Affero General Public License v3
Classifier: Natural Language :: English
Classifier: Programming Language :: Python :: 2
Classifier: Programming Language :: Python :: 2.6
Classifier: Programming Language :: Python :: 2.7
Classifier: Programming Language :: Python :: 3
Classifier: Programming Language :: Python :: 3.4
Classifier: Programming Language :: Python :: 3.5
Classifier: Programming Language :: Python :: 3.6
Classifier: Programming Language :: Python :: 3.7
Classifier: Topic :: Utilities
Requires-Dist: boto3
Requires-Dist: paramiko
Requires-Dist: awscli
